tailwind_merge/__init__.py
tailwind_merge/core.py
tailwind_merge-0.3.3.dist-info/LICENSE
tailwind_merge-0.3.3.dist-info/METADATA
tailwind_merge-0.3.3.dist-info/WHEEL
tailwind_merge-0.3.3.dist-info/RECORD
