Metadata-Version: 2.1
Name: tailwind-merge
Version: 0.3.3
Summary: Merge Tailwind CSS classes without conflicts in python.
License: MIT
Keywords: python,tailwind,css,merge
Author: Will Abbott
Author-email: willabb83@gmail.com
Requires-Python: >=3.8,<4.0
Classifier: License :: OSI Approved :: MIT License
Classifier: Operating System :: OS Independent
Classifier: Programming Language :: Python :: 3
Classifier: Programming Language :: Python :: 3.8
Classifier: Programming Language :: Python :: 3.9
Classifier: Programming Language :: Python :: 3.10
Classifier: Programming Language :: Python :: 3.11
Classifier: Programming Language :: Python :: 3.12
Classifier: Programming Language :: Python :: 3.13
Project-URL: Bug Tracker, https://github.com/wrabit/tailwind-merge-python/issues
Project-URL: Homepage, https://github.com/wrabit/tailwind-merge-python
